iflow_mcp_mcp_outline-1.1.4.dev0.dist-info/licenses/LICENSE
mcp_outline/__init__.py
mcp_outline/__main__.py
mcp_outline/server.py
mcp_outline/features/__init__.py
mcp_outline/features/health.py
mcp_outline/features/documents/__init__.py
mcp_outline/features/documents/ai_tools.py
mcp_outline/features/documents/batch_operations.py
mcp_outline/features/documents/collection_tools.py
mcp_outline/features/documents/common.py
mcp_outline/features/documents/document_collaboration.py
mcp_outline/features/documents/document_content.py
mcp_outline/features/documents/document_lifecycle.py
mcp_outline/features/documents/document_organization.py
mcp_outline/features/documents/document_reading.py
mcp_outline/features/documents/document_search.py
mcp_outline/features/resources/__init__.py
mcp_outline/features/resources/collection_resources.py
mcp_outline/features/resources/document_resources.py
mcp_outline/patches/__init__.py
mcp_outline/patches/copilot_cli.py
mcp_outline/utils/__init__.py
mcp_outline/utils/outline_client.py
iflow_mcp_mcp_outline-1.1.4.dev0.dist-info/METADATA
iflow_mcp_mcp_outline-1.1.4.dev0.dist-info/WHEEL
iflow_mcp_mcp_outline-1.1.4.dev0.dist-info/entry_points.txt
iflow_mcp_mcp_outline-1.1.4.dev0.dist-info/top_level.txt
iflow_mcp_mcp_outline-1.1.4.dev0.dist-info/RECORD
