Metadata-Version: 2.4
Name: iflow-mcp_mcp-outline
Version: 1.1.4.dev0
Summary: A Model Context Protocol (MCP) server for Outline (https://www.getoutline.com)
Author-email: "Atle H. Havsø" <atle@havso.net>
Project-URL: Homepage, https://github.com/Vortiago/mcp-outline
Project-URL: Bug Tracker, https://github.com/Vortiago/mcp-outline/issues
Requires-Python: >=3.10
License-File: LICENSE
Requires-Dist: mcp[cli]>=1.20.0
Requires-Dist: httpx>=0.27.0
Provides-Extra: dev
Requires-Dist: mcp[cli]>=1.20.0; extra == "dev"
Requires-Dist: pytest>=8.4.0; extra == "dev"
Requires-Dist: pytest-asyncio>=1.2.0; extra == "dev"
Requires-Dist: pytest-cov>=6.0.0; extra == "dev"
Requires-Dist: ruff>=0.14.0; extra == "dev"
Requires-Dist: anyio>=4.11.0; extra == "dev"
Requires-Dist: pyright>=1.1.407; extra == "dev"
Requires-Dist: trio>=0.31.0; extra == "dev"
Requires-Dist: pre-commit>=4.0.0; extra == "dev"
Dynamic: license-file
